README.rst
setup.cfg
setup.py
payu_biz/__init__.py
payu_biz/payu_config.py
payu_biz/payu_hash.py
payu_biz/payubiz.py
payu_biz/views.py
payu_biz.egg-info/PKG-INFO
payu_biz.egg-info/SOURCES.txt
payu_biz.egg-info/dependency_links.txt
payu_biz.egg-info/top_level.txt