Metadata-Version: 1.1
Name: payu-biz
Version: 1.3.1
Summary:  payu payment gateway package for django
Home-page: https://github.com/renjithsraj/django_payubiz/tree/master/payu_biz
Author: Renjith S Raj
Author-email: renjithsraj@live.com
License: MIT
Download-URL: https://github.com/renjithsraj/django_payubiz/archive/0.1.tar.gz
Keywords: payu payment gateway package django,payment gateway python package,payu,payu python package,payment gateway,payu gateway django,django gateway package
Platform: UNKNOWN
Classifier: Development Status :: 4 - Beta
Classifier: Topic :: Internet
Classifier: License :: OSI Approved :: MIT License
Classifier: Intended Audience :: Developers
Classifier: Environment :: Web Environment
Classifier: Programming Language :: Python
Classifier: Programming Language :: Python :: 2.6
Classifier: Programming Language :: Python :: 2.7
Classifier: Programming Language :: Python :: 3
